{"latestDate":"2026-05-13","prevDate":"2026-05-12","mode":"weight","threshold":0.5,"globalETFs":["TIME 글로벌탑픽액티브","TIME 글로벌바이오액티브","TIME 글로벌우주테크&방산액티브","TIME 미국S&P500액티브","TIME 차이나AI테크액티브","TIME 글로벌AI인공지능액티브","TIME 미국나스닥100액티브","TIME 미국배당다우존스액티브","TIME 미국나스닥100채권혼합50액티브","TIME 글로벌소비트렌드액티브"],"domesticETFs":["TIME K신재생에너지액티브","TIME K바이오액티브","TIME Korea플러스배당액티브","TIME 코스피액티브","TIME 코리아밸류업액티브","TIME K이노베이션액티브","TIME K컬처액티브","TIME 코스닥액티브"],"summaries":{"TIME 글로벌탑픽액티브":{"newIn":[],"newOut":[["ESM6 Index","S&P500 EMINI FUT JUN 2026",2.66]],"buys":[["SPGM US EQUITY","State Street SPDR Portfolio MSCI Global Stock Market ETF",0.5399999999999991]],"sells":[]},"TIME K신재생에너지액티브":{"newIn":[],"newOut":[],"buys":[],"sells":[["006400","삼성SDI",-0.5099999999999998]]},"TIME 글로벌바이오액티브":{"newIn":[],"newOut":[],"buys":[],"sells":[]},"TIME 글로벌우주테크&방산액티브":{"newIn":[],"newOut":[["BSP GY EQUITY","BAE Systems PLC",0.97]],"buys":[["RKLB US EQUITY","Rocket Lab Corp",1.2599999999999998]],"sells":[]},"TIME 미국S&P500액티브":{"newIn":[],"newOut":[],"buys":[],"sells":[]},"TIME K바이오액티브":{"newIn":[],"newOut":[["001060","JW중외제약",0.35]],"buys":[["128940","한미약품",1.75],["141080","리가켐바이오",0.54]],"sells":[["397030","에이프릴바이오",-0.7700000000000005]]},"TIME 차이나AI테크액티브":{"newIn":[],"newOut":[],"buys":[["002865 CH EQUITY","Hainan Drinda New Energy Technology Co Ltd",1.04]],"sells":[]},"TIME 글로벌AI인공지능액티브":{"newIn":[],"newOut":[],"buys":[],"sells":[]},"TIME Korea플러스배당액티브":{"newIn":[],"newOut":[],"buys":[],"sells":[]},"TIME 미국나스닥100액티브":{"newIn":[],"newOut":[],"buys":[],"sells":[]},"TIME 미국배당다우존스액티브":{"newIn":[],"newOut":[],"buys":[["ESM6 Index","S&P500 EMINI FUT JUN 2026",1.6300000000000003],["QCOM US EQUITY","QUALCOMM Inc",0.8899999999999988],["TXN US EQUITY","Texas Instruments Inc",0.7700000000000005],["UNH US EQUITY","UnitedHealth Group Inc",0.5600000000000005]],"sells":[["AVGO US EQUITY","Broadcom Inc",-0.6399999999999997],["SNDK US EQUITY","Sandisk Corp/DE",-0.5700000000000003]]},"TIME 미국나스닥100채권혼합50액티브":{"newIn":[],"newOut":[],"buys":[],"sells":[]},"TIME 코스피액티브":{"newIn":[],"newOut":[],"buys":[],"sells":[]},"TIME 글로벌소비트렌드액티브":{"newIn":[["9988 HK EQUITY","Alibaba Group Holding Ltd",1.58]],"newOut":[],"buys":[],"sells":[]},"TIME 코리아밸류업액티브":{"newIn":[],"newOut":[],"buys":[],"sells":[]},"TIME K이노베이션액티브":{"newIn":[],"newOut":[["452280","한선엔지니어링",0.99],["082740","한화엔진",2.47]],"buys":[["005490","POSCO홀딩스",2.09],["036930","주성엔지니어링",1.0099999999999998],["006400","삼성SDI",0.9599999999999991],["178320","서진시스템",0.9300000000000002],["108490","로보티즈",0.71],["036570","NC",0.6200000000000001],["476830","알지노믹스",0.53]],"sells":[["078600","대주전자재료",-1.25],["052400","코나아이",-1.1900000000000002],["010120","LS ELECTRIC",-0.95],["064290","인텍플러스",-0.7999999999999998]]},"TIME K컬처액티브":{"newIn":[],"newOut":[],"buys":[["483650","달바글로벌",0.8100000000000005]],"sells":[]},"TIME 코스닥액티브":{"newIn":[],"newOut":[],"buys":[["277810","레인보우로보틱스",1.5200000000000005]],"sells":[]}}}