{"latestDate":"2026-04-28","prevDate":"2026-04-27","mode":"shares","threshold":10,"globalETFs":["TIME 글로벌탑픽액티브","TIME 글로벌바이오액티브","TIME 글로벌우주테크&방산액티브","TIME 미국S&P500액티브","TIME 차이나AI테크액티브","TIME 글로벌AI인공지능액티브","TIME 미국나스닥100액티브","TIME 미국배당다우존스액티브","TIME 미국나스닥100채권혼합50액티브","TIME 글로벌소비트렌드액티브"],"domesticETFs":["TIME K신재생에너지액티브","TIME K바이오액티브","TIME Korea플러스배당액티브","TIME 코스피액티브","TIME 코리아밸류업액티브","TIME K이노베이션액티브","TIME K컬처액티브","TIME 코스닥액티브"],"summaries":{"TIME 글로벌탑픽액티브":{"newIn":[],"newOut":[],"buys":[["SPGM US EQUITY","State Street SPDR Portfolio MSCI Global Stock Market ETF",14]],"sells":[["VEA US EQUITY","Vanguard FTSE Developed Markets ETF",-37]]},"TIME K신재생에너지액티브":{"newIn":[],"newOut":[],"buys":[],"sells":[]},"TIME 글로벌바이오액티브":{"newIn":[],"newOut":[],"buys":[["TEVA US EQUITY","Teva Pharmaceutical Industries Ltd",23],["NVO US EQUITY","Novo Nordisk A/S",17],["MRNA US EQUITY","Moderna Inc",11],["EXEL US EQUITY","Exelixis Inc",11],["ARWR US EQUITY","Arrowhead Pharmaceuticals Inc",10],["TERN US EQUITY","Terns Pharmaceuticals Inc",10],["GPCR US EQUITY","Structure Therapeutics Inc",10]],"sells":[["LLY US EQUITY","Eli Lilly & Co",-20]]},"TIME 글로벌우주테크&방산액티브":{"newIn":[["443060","HD현대마린솔루션",50]],"newOut":[],"buys":[],"sells":[]},"TIME 미국S&P500액티브":{"newIn":[],"newOut":[],"buys":[],"sells":[]},"TIME K바이오액티브":{"newIn":[],"newOut":[],"buys":[["226950","올릭스",100],["141080","리가켐바이오",50]],"sells":[["068270","셀트리온",-44],["207940","삼성바이오로직스",-10]]},"TIME 차이나AI테크액티브":{"newIn":[["HCTK6 Index","HSTECH INDEX FUT MAY 2026",0]],"newOut":[["HCTJ6 Index","HSTECH Futures APR26",0]],"buys":[["981 HK EQUITY","Semiconductor Manufacturing International Corp",1176],["1347 HK EQUITY","Hua Hong Semiconductor Ltd",699],["002384 CH EQUITY","Suzhou Dongshan Precision Manufacturing Co Ltd",17]],"sells":[["002050 CH EQUITY","Zhejiang Sanhua Intelligent Controls Co Ltd",-495],["002028 CH EQUITY","Sieyuan Electric Co Ltd",-100],["300502 CH EQUITY","Eoptolink Technology Inc Ltd",-44],["100 HK EQUITY","Minimax Group Inc",-34],["6770 TT EQUITY","Powerchip Semiconductor Manufacturing Corp",-29],["300308 CH EQUITY","Zhongji Innolight Co Ltd",-26],["2337 TT EQUITY","Macronix International Co Ltd",-19],["3481 TT EQUITY","Innolux Corp",-18],["9660 HK EQUITY","Horizon Robotics",-17],["2408 TT EQUITY","Nanya Technology Corp",-14],["3711 TT EQUITY","ASE Technology Holding Co Ltd",-11]]},"TIME 글로벌AI인공지능액티브":{"newIn":[["267260","HD현대일렉트릭",8]],"newOut":[],"buys":[["440110","파두",137],["BE US EQUITY","Bloom Energy Corp",31],["AMZN US EQUITY","Amazon.com Inc",28],["MSFT US EQUITY","Microsoft Corp",17],["STX US EQUITY","Seagate Technology Holdings PLC",12]],"sells":[["CRCL US EQUITY","Circle Internet Group Inc",-24],["MSTR US EQUITY","Strategy Inc",-23],["COIN US EQUITY","Coinbase Global Inc",-19],["0043Y0","TIME 차이나AI테크액티브",-15],["SIMO US EQUITY","Silicon Motion Technology Corp",-15],["META US EQUITY","Meta Platforms Inc",-11]]},"TIME Korea플러스배당액티브":{"newIn":[],"newOut":[],"buys":[],"sells":[]},"TIME 미국나스닥100액티브":{"newIn":[],"newOut":[],"buys":[["BE US EQUITY","Bloom Energy Corp",54],["MSFT US EQUITY","Microsoft Corp",29],["AAPL US EQUITY","Apple Inc",23],["STX US EQUITY","Seagate Technology Holdings PLC",16]],"sells":[["CRCL US EQUITY","Circle Internet Group Inc",-65],["NVDA US EQUITY","NVIDIA Corp",-48],["NBIS US EQUITY","Nebius Group NV",-43],["SIMO US EQUITY","Silicon Motion Technology Corp",-42],["COIN US EQUITY","Coinbase Global Inc",-32]]},"TIME 미국배당다우존스액티브":{"newIn":[],"newOut":[],"buys":[["QCOM US EQUITY","QUALCOMM Inc",54]],"sells":[["COP US EQUITY","ConocoPhillips",-33],["TXN US EQUITY","Texas Instruments Inc",-15],["AVGO US EQUITY","Broadcom Inc",-10]]},"TIME 미국나스닥100채권혼합50액티브":{"newIn":[],"newOut":[["FTAI US EQUITY","FTAI Aviation Ltd",8]],"buys":[["272580","TIGER 단기채권액티브",157],["BE US EQUITY","Bloom Energy Corp",12]],"sells":[["190620","ACE 단기통안채",-39],["122260","KIWOOM 통안채1년",-18],["CRCL US EQUITY","Circle Internet Group Inc",-15],["NVDA US EQUITY","NVIDIA Corp",-13],["NBIS US EQUITY","Nebius Group NV",-13],["196230","RISE 단기통안채",-12]]},"TIME 코스피액티브":{"newIn":[["329180","HD현대중공업",90]],"newOut":[["082920","비츠로셀",1182]],"buys":[["008770","호텔신라",399],["006260","LS",80]],"sells":[["005380","현대차",-30],["003230","삼양식품",-25],["079550","LIG디펜스앤에어로스페이스",-10]]},"TIME 글로벌소비트렌드액티브":{"newIn":[],"newOut":[],"buys":[],"sells":[]},"TIME 코리아밸류업액티브":{"newIn":[["036930","주성엔지니어링",55]],"newOut":[["000270","기아",28],["316140","우리금융지주",338]],"buys":[["006800","미래에셋증권",82],["005930","삼성전자",23]],"sells":[["039490","키움증권",-18]]},"TIME K이노베이션액티브":{"newIn":[["082740","한화엔진",500],["241520","DSC인베스트먼트",2500]],"newOut":[["281740","레이크머티리얼즈",1597],["356860","티엘비",380],["107640","한중엔시에스",501]],"buys":[["036930","주성엔지니어링",150],["440110","파두",100]],"sells":[["079550","LIG디펜스앤에어로스페이스",-19]]},"TIME K컬처액티브":{"newIn":[],"newOut":[],"buys":[],"sells":[]},"TIME 코스닥액티브":{"newIn":[["033640","네패스",280]],"newOut":[],"buys":[["417200","LS머트리얼즈",300],["078600","대주전자재료",90],["171090","선익시스템",20]],"sells":[["440110","파두",-138],["100790","미래에셋벤처투자",-106],["095610","테스",-49],["476830","알지노믹스",-47],["183300","코미코",-29],["240810","원익IPS",-24]]}}}